ckanext/__init__.py
ckanext/bulk/__init__.py
ckanext/bulk/const.py
ckanext/bulk/helpers.py
ckanext/bulk/interfaces.py
ckanext/bulk/plugin.py
ckanext/bulk/utils.py
ckanext/bulk/views.py
ckanext/bulk/assets/webassets.yml
ckanext/bulk/assets/scripts/bulk-manager-form.js
ckanext/bulk/assets/scripts/bulk-tom-select.js
ckanext/bulk/assets/scripts/bulk.js
ckanext/bulk/assets/styles/bulk.css
ckanext/bulk/assets/vendor/htmx.js
ckanext/bulk/assets/vendor/prism.min.css
ckanext/bulk/assets/vendor/prism.min.js
ckanext/bulk/assets/vendor/sweetalert2.all.js
ckanext/bulk/assets/vendor/tom-select.complete.min.js
ckanext/bulk/entity_managers/__init__.py
ckanext/bulk/entity_managers/base.py
ckanext/bulk/entity_managers/dataset.py
ckanext/bulk/entity_managers/group.py
ckanext/bulk/entity_managers/organization.py
ckanext/bulk/entity_managers/resource.py
ckanext/bulk/logic/__init__.py
ckanext/bulk/logic/action.py
ckanext/bulk/logic/auth.py
ckanext/bulk/logic/schema.py
ckanext/bulk/logic/validators.py
ckanext/bulk/templates/header.html
ckanext/bulk/templates/bulk/error.html
ckanext/bulk/templates/bulk/form.html
ckanext/bulk/templates/bulk/manager.html
ckanext/bulk/templates/bulk/manager_accordion.html
ckanext/bulk/templates/bulk/manager_form.html
ckanext/bulk/templates/bulk/manager_info.html
ckanext/bulk/templates/bulk/form/tom_select.html
ckanext/bulk/templates/bulk/snippets/filter_item.html
ckanext/bulk/templates/bulk/snippets/update_item.html
ckanext/bulk/tests/__init__.py
ckanext/bulk/tests/conftest.py
ckanext/bulk/tests/test_interface.py
ckanext/bulk/tests/entity_managers/test_dataset.py
ckanext/bulk/tests/entity_managers/test_group.py
ckanext/bulk/tests/entity_managers/test_organization.py
ckanext/bulk/tests/entity_managers/test_resource.py
ckanext_bulk-0.4.0.dist-info/licenses/LICENSE
ckanext_bulk-0.4.0.dist-info/METADATA
ckanext_bulk-0.4.0.dist-info/WHEEL
ckanext_bulk-0.4.0.dist-info/entry_points.txt
ckanext_bulk-0.4.0.dist-info/top_level.txt
ckanext_bulk-0.4.0.dist-info/RECORD
